haistings/__init__.py
haistings/haistings.py
haistings/k8sreport.py
haistings/memory.py
haistings/prompts.py
haistings/repo_ingest.py
haistings/vector_db.py
haistings-0.0.2.dist-info/METADATA
haistings-0.0.2.dist-info/WHEEL
haistings-0.0.2.dist-info/entry_points.txt
haistings-0.0.2.dist-info/RECORD
