Metadata-Version: 2.1
Name: haistings
Version: 0.0.2
Summary: AI-powered CVE prioritizer
License: Apache-2.0
Author: Stacklok Inc
Requires-Python: >=3.12,<3.13
Classifier: License :: OSI Approved :: Apache Software License
Classifier: Programming Language :: Python :: 3
Classifier: Programming Language :: Python :: 3.12
Requires-Dist: argparse (==1.4.0)
Requires-Dist: gitingest (==0.1.3)
Requires-Dist: gitpython (==3.1.44)
Requires-Dist: huggingface-hub (==0.23.0)
Requires-Dist: kubernetes (==32.0.1)
Requires-Dist: langchain-community (==0.3.17)
Requires-Dist: langchain-huggingface (==0.1.2)
Requires-Dist: langchain[openai] (==0.3.18)
Requires-Dist: langchainhub (==0.1.21)
Requires-Dist: langgraph-checkpoint-sqlite (==2.0.5)
Requires-Dist: langgraph[sqlite] (==0.2.73)
Requires-Dist: numpy (==2.2.3)
Requires-Dist: ruff (==0.9.9)
Requires-Dist: sentence-transformers (==3.4.1)
